{
    "id": "logic-app-standard",
    "version": "0.0.6",
    "name": "Logic App Standard",
    "description": "A template for a Logic App Standard dev container.",
    "documentationUrl": "",
    "licenseUrl": "https://github.com/mcollier/logic-app-dev-container-template/blob/main/LICENSE",
    "publisher": "Community",
    "options": {
        "imageVariant": {
            "type": "string",
            "description": "Debian version (use bullseye on local arm64/Apple Silicon)",
            "proposals": [
                "bullseye",
                "buster"
            ],
            "default": "bullseye"
        }
    },
    "platforms": [
        "Any"
    ]
}